Workbook

Sheet Equipo
A1: EQUIPO DE TRABAJO - PROYECTO PANDA NAICHA
A3: Proyecto | B3: Sistema Web de Gestión Centralizada de Ventas con Árboles de Decisiones - Panda Naicha
A4: Materia | B4: Proyecto de Sistemas 3
A5: Fecha de entrega | B5: 11/06/2026
A7: INTEGRANTES | B7: NOMBRE COMPLETO
A8: Integrante 1 | B8: Jean Marco Mendoza Aliaga
A9: Integrante 2 | B9: Javier Morales Gutierrez
A10: Integrante 3 | B10: Jesus Alexander Santander Amaru

Sheet Gestion de Modulos
A1: MODULOS
A2: Login
A3: Gestion Usuarios
A4: Apertura de Turno
A5: Registro de Ventas
A6: Movimientos de Caja
A7: Cierre de Turno
A8: Arbol de Decisiones
A9: Reportes
A10: Vitrina Publica
A11: Mapa Google Maps
A12: Validacion de Botones

Sheet Test Plan
A2: Modulo (Dropdown) | B2: Test Case | C2: Descripción | D2: Precondiciones | E2: Resultado Esperado | F2: Resultado Actual (Si falla) | G2: Ultima ejecución (Fecha) | H2: Estado (Dropdown) | I2: Comentario
A3: Login | B3: Inicio de sesion con credenciales validas | C3: El sistema valida usuario y contrasena y redirige al panel segun el rol del usuario autenticado. | D3: Existir al menos un usuario activo en la base de datos (admin o cajero). | E3: Redireccion al panel administrativo (/admin/dashboard) o al modulo de turno (/cajero) segun corresponda. Sesion Laravel generada y cookie segura emitida. | G3: 46181 | H3: PASS | I3: Validado para admin y cajero
A4: Login | B4: Login con credenciales invalidas | C4: El sistema rechaza el intento de login y muestra un mensaje de error sin revelar si el problema es el usuario o la contrasena. | D4: No haber iniciado sesion previamente. | E4: Mensaje de error generico mostrado en pantalla. Permanece en la vista de login sin generar sesion. | G4: 46181 | H4: PASS | I4: Mensaje generico por seguridad
A5: Login | B5: Cierre de sesion (logout) | C5: El sistema cierra la sesion activa del usuario y lo redirige a la pantalla de login. | D5: Tener una sesion activa iniciada. | E5: Sesion destruida en el servidor. Cookie eliminada del navegador. Redireccion a /login. | G5: 46181 | H5: PASS
A6: Gestion Usuarios | B6: Crear nuevo cajero | C6: El administrador puede registrar un nuevo cajero con nombre, username, contrasena y sucursal asignada. | D6: Tener sesion activa como administrador. | E6: Usuario creado en la tabla users con rol cajero, password almacenada como hash bcrypt y registro visible en el listado. | G6: 46181 | H6: PASS | I6: Password se almacena hasheada
A7: Gestion Usuarios | B7: Listar usuarios del sistema | C7: El administrador visualiza el listado de todos los usuarios registrados, paginado y filtrable por rol. | D7: Tener sesion activa como administrador. Existir al menos un usuario adicional. | E7: Tabla mostrando id, nombre, username, rol, estado y acciones disponibles para cada registro. | G7: 46181 | H7: PASS
A8: Gestion Usuarios | B8: Editar datos de un cajero existente | C8: El administrador modifica el nombre, email o sucursal de un cajero ya registrado. | D8: Tener sesion activa como administrador. Existir el cajero a editar. | E8: Cambios persistidos en la tabla users. Confirmacion visual mostrada y datos actualizados en el listado. | G8: 46181 | H8: PASS
A9: Gestion Usuarios | B9: Desactivar cajero | C9: El administrador desactiva un cajero existente impidiendole iniciar sesion sin eliminar el registro de la base de datos. | D9: Tener sesion activa como administrador. Existir un cajero activo. | E9: Campo is_active del usuario actualizado a false. El cajero ya no puede iniciar sesion y sus datos historicos se preservan. | G9: 46181 | H9: PASS | I9: Soft delete - preserva historico
A10: Apertura de Turno | B10: Apertura de turno por administrador | C10: El administrador apertura un turno para un cajero registrando el stock inicial por producto. | D10: Tener sesion activa como administrador. El cajero no debe tener un turno OPEN activo. | E10: Registro creado en la tabla shifts con status OPEN, registros en shift_stocks con cantidades iniciales, y timestamp de apertura. | G10: 46181 | H10: PASS | I10: Cajero NO abre su propio turno por diseno
A11: Apertura de Turno | B11: Validacion de stock inicial obligatorio | C11: El sistema impide aperturar un turno sin ingresar el stock inicial de los productos. | D11: Tener sesion activa como administrador. Intentar aperturar dejando campos de stock vacios. | E11: Mensaje de validacion mostrado en formulario. No se crea registro en shifts ni en shift_stocks. | G11: 46181 | H11: PASS
A12: Apertura de Turno | B12: Pantalla de espera del cajero sin turno asignado | C12: El cajero que inicia sesion sin un turno aperturado por el admin ve una pantalla de espera y no puede acceder a ventas. | D12: Tener sesion activa como cajero. No existir un turno OPEN asociado al cajero. | E12: Redireccion automatica a /cajero/turno/espera. No se permite navegar a /cajero/ventas hasta que el admin apertura un turno. | G12: 46181 | H12: PASS | I12: Decision de diseno documentada
A13: Registro de Ventas | B13: Registro de venta en efectivo | C13: El cajero registra una venta seleccionando producto, cantidad y metodo de pago CASH. | D13: Tener sesion activa como cajero con turno OPEN. Existir productos activos con stock disponible. | E13: Registro creado en sales con payment_method=CASH y status=COMPLETED. Detalles en sale_details. Stock descontado en shift_stocks. Total del turno actualizado. | G13: 46181 | H13: PASS
A14: Registro de Ventas | B14: Registro de venta por QR | C14: El cajero registra una venta seleccionando el metodo de pago QR. | D14: Tener sesion activa como cajero con turno OPEN. | E14: Registro creado en sales con payment_method=QR. La proporcion de ventas QR se actualiza para el calculo del arbol de decisiones al cierre. | G14: 46181 | H14: PASS | I14: Relevante para el arbol de decisiones
A15: Registro de Ventas | B15: Validacion de venta sin turno activo | C15: El sistema impide registrar ventas si no existe un turno OPEN para el cajero. | D15: Tener sesion como cajero sin turno aperturado. | E15: Acceso bloqueado a /cajero/ventas. Mensaje informando que requiere turno aperturado por el administrador. | G15: 46181 | H15: PASS
A16: Movimientos de Caja | B16: Registro de egreso operativo | C16: El cajero registra un egreso indicando monto, categoria y descripcion. | D16: Tener turno OPEN activo. | E16: Registro creado en cash_movements con movement_type=EXPENSE. El egreso se descuenta del total esperado al momento del cierre. | G16: 46181 | H16: PASS
A17: Movimientos de Caja | B17: Registro de ingreso extraordinario | C17: El cajero registra un ingreso extraordinario (ejemplo: pago de cliente pendiente) con descripcion justificativa. | D17: Tener turno OPEN activo. | E17: Registro creado en cash_movements con movement_type=INCOME. El ingreso suma al total esperado del turno. | G17: 46181 | H17: PASS
A18: Movimientos de Caja | B18: Validacion de movimiento sin descripcion | C18: El sistema obliga al cajero a ingresar una descripcion al registrar un egreso o ingreso para mantener trazabilidad. | D18: Tener turno OPEN activo. Intentar registrar movimiento sin descripcion. | E18: Mensaje de validacion mostrado. No se crea el registro en cash_movements hasta completar el campo. | G18: 46181 | H18: PASS | I18: Cumple requisito de auditoria
A19: Cierre de Turno | B19: Cierre con monto fisico exacto | C19: El cajero ingresa el monto fisico contado igual al total esperado, generando diferencia cero. | D19: Tener turno OPEN con al menos una venta registrada. | E19: Turno actualizado a status=CLOSED. difference=0. El arbol clasifica el cierre como SIN_INCONSISTENCIA. | G19: 46181 | H19: PASS | I19: Caso base del arbol de decisiones
A20: Cierre de Turno | B20: Cierre con diferencia detectada | C20: El cajero ingresa un monto fisico distinto al esperado y el sistema calcula la diferencia y la clasifica. | D20: Tener turno OPEN. Ingresar un monto fisico distinto al esperado. | E20: Diferencia calculada y almacenada en shifts.difference. Arbol invocado y resultado almacenado en inconsistency_class y decision_path. | G20: 46181 | H20: PASS
A21: Cierre de Turno | B21: Notas de traspaso al siguiente cajero | C21: El cajero puede agregar observaciones libres durante el cierre que quedan visibles para el administrador y el siguiente turno. | D21: Tener turno en proceso de cierre. | E21: Campo notes de la tabla shifts almacena el texto ingresado. Visible en el panel de administrador. | G21: 46181 | H21: PASS
A22: Arbol de Decisiones | B22: Clasificacion: sin inconsistencia (diferencia=0) | C22: El arbol de decisiones clasifica como SIN_INCONSISTENCIA cuando el monto fisico declarado coincide con el esperado. | D22: Cierre con monto fisico = total esperado. | E22: inconsistency_class = SIN_INCONSISTENCIA. decision_path registra la rama recorrida. Cierre aprobado automaticamente. | G22: 46181 | H22: PASS | I22: Rama 1 del arbol - caso optimo
A23: Arbol de Decisiones | B23: Clasificacion: inconsistencia leve por error humano | C23: Cuando la diferencia es menor o igual a Bs 20 y el cajero no es reincidente, el arbol clasifica como LEVE. | D23: Cierre con diferencia <= Bs 20. Cajero con historial limpio (menos de 2 inconsistencias en ultimos 3 turnos). | E23: inconsistency_class = INCONSISTENCIA_LEVE. Cierre operativo aprobado. Registro queda para revision rutinaria. | G23: 46181 | H23: PASS | I23: Rama 2 del arbol
A24: Arbol de Decisiones | B24: Clasificacion: critica por reincidencia | C24: Cuando la diferencia es leve pero el cajero acumula 2 o mas inconsistencias en sus ultimos 3 turnos, el arbol escala a CRITICA. | D24: Cierre con diferencia <= Bs 20. Cajero con historial de 2 o mas turnos previos con inconsistencia. | E24: inconsistency_class = INCONSISTENCIA_CRITICA. decision_path registra el motivo (reincidencia). Notificacion al administrador. | G24: 46181 | H24: PASS | I24: Rama 3 - deteccion de patron
A25: Arbol de Decisiones | B25: Clasificacion: critica por sobrante sin egresos | C25: Cuando la diferencia es mayor a Bs 20 con sobrante de caja y no hay egresos registrados, se clasifica como CRITICA. | D25: Cierre con diferencia > Bs 20 (sobrante). Cero registros en cash_movements de tipo EXPENSE. | E25: inconsistency_class = INCONSISTENCIA_CRITICA. decision_path indica posibles ventas no registradas. | G25: 46181 | H25: PASS | I25: Rama 7 - posible irregularidad
A26: Reportes | B26: Generacion de reporte diario | C26: El administrador genera el reporte de cierre diario consolidando ventas, egresos, ingresos y saldo neto. | D26: Tener sesion activa como administrador. Existir al menos un turno cerrado en el dia. | E26: Vista de reporte mostrando totales de ventas, egresos, ingresos y saldo neto agrupados por turno y cajero. | G26: 46181 | H26: PASS
A27: Reportes | B27: Filtrado de reporte por rango de fechas | C27: El administrador filtra los reportes seleccionando una fecha inicial y final. | D27: Existir turnos cerrados en fechas distintas. | E27: Reporte muestra unicamente los turnos cuyo close_time se encuentra dentro del rango seleccionado. | G27: 46181 | H27: PASS
A28: Reportes | B28: Exportacion de reporte a PDF | C28: El administrador exporta un reporte a PDF utilizando la funcion de impresion nativa del navegador. | D28: Tener un reporte generado en pantalla. | E28: Apertura de dialogo de impresion del navegador con vista optimizada (sin menus, sin botones de UI). Conversion correcta a PDF. | G28: 46181 | H28: PASS | I28: Impresion nativa - sin librerias externas
A29: Vitrina Publica | B29: Carga de la landing page publica | C29: Un visitante sin autenticacion accede a la pagina principal del negocio y visualiza todas las secciones. | D29: Tener el servidor activo. Acceder a la URL raiz del sistema. | E29: Pagina carga correctamente con secciones de hero, sobre nosotros, catalogo, ubicacion, horarios y footer. Tiempo de carga < 3 segundos. | G29: 46181 | H29: PASS
A30: Vitrina Publica | B30: Catalogo dinamico de productos | C30: El catalogo publico muestra los productos activos consultados directamente desde la base de datos del sistema interno. | D30: Existir productos con is_active=true en la tabla products. | E30: Catalogo renderiza una tarjeta por cada producto activo mostrando nombre, ilustracion, precio y categoria. Productos inactivos NO aparecen. | G30: 46181 | H30: PASS | I30: Renderizado server-side via Blade
A31: Vitrina Publica | B31: Filtro del catalogo por categoria | C31: El visitante filtra el catalogo seleccionando entre Todos, Bebidas y Toppings. | D31: Existir productos activos de ambas categorias en la tabla products. | E31: Al seleccionar "Bebidas" solo se muestran productos con category=BEBIDA. Al seleccionar "Toppings" solo los TOPPING. "Todos" restablece la vista completa. | G31: 46181 | H31: PASS | I31: Columna category agregada en Sprint 4
A32: Vitrina Publica | B32: Disenio responsive en dispositivos moviles | C32: La landing se adapta correctamente a viewports moviles manteniendo legibilidad y usabilidad. | D32: Acceder al sitio desde un dispositivo movil o emulador con ancho de pantalla menor a 768px. | E32: Layout reorganiza tarjetas a una sola columna. Menu hamburguesa visible. Botones flotantes y mapa correctamente escalados. | G32: 46181 | H32: PASS | I32: Bootstrap 5 + media queries
A33: Mapa Google Maps | B33: Visualizacion del mapa integrado en la landing | C33: El mapa de Google Maps embebido carga correctamente mostrando la ubicacion exacta del local en Av. 20 de Octubre 2038, La Paz. | D33: Tener conexion a internet activa. Acceder a la seccion de ubicacion de la landing. | E33: Iframe de Google Maps renderiza centrado en la direccion del local. Marcador visible. Permite zoom in/out y arrastre dentro del iframe. | G33: 46181 | H33: PASS | I33: Embed sin API key requerida
A34: Mapa Google Maps | B34: Boton "Como llegar" abre indicaciones de ruta | C34: El boton "Como llegar" abre Google Maps en una nueva pestania con la direccion del local pre-cargada como destino. | D34: Estar en la seccion de ubicacion de la landing. | E34: Click en el boton abre nueva pestania en https://www.google.com/maps/dir/?api=1&destination=... con el destino correctamente cargado. | G34: 46181 | H34: PASS | I34: Funciona en escritorio y movil
A35: Validacion de Botones | B35: Boton flotante de WhatsApp visible en toda la pagina | C35: El boton flotante de WhatsApp se mantiene fijo en la esquina inferior derecha durante toda la navegacion de la landing. | D35: Acceder a la landing publica. | E35: Boton visible en posicion fixed bottom-right con animacion pulse. Visible en todas las secciones al hacer scroll. Al hacer click abre wa.me con mensaje pre-llenado generico. | G35: 46181 | H35: PASS | I35: Numero: +591 72088603
A36: Validacion de Botones | B36: Boton "Consultar" por producto abre WhatsApp con mensaje dinamico | C36: Cada tarjeta del catalogo tiene un boton "Consultar" que abre WhatsApp pre-cargando el nombre del producto en el mensaje. | D36: Existir productos en el catalogo publico. | E36: Click en "Consultar" sobre un producto X abre wa.me/59172088603?text=Hola, quiero consultar por: X. El mensaje codifica correctamente los caracteres especiales. | G36: 46181 | H36: PASS | I36: urlencode aplicado correctamente
A37: Validacion de Botones | B37: Boton "Volver al inicio" desde el login | C37: La pantalla de login incluye un boton que retorna a la landing publica sin requerir autenticacion. | D37: Acceder a la URL /login sin sesion activa. | E37: Boton visible en la esquina superior izquierda. Click redirige a la ruta / (landing publica) sin afectar el formulario de login. | G37: 46181 | H37: PASS | I37: Agregado en Sprint 4

Sheet Stats
A1: RESUMEN POR MODULO Y ESTADO
A3: Modulo | B3: PASS | C3: FAIL | D3: PENDING | E3: Total
A4: Login | B4: =COUNTIFS('Test Plan'!$A:$A,A4,'Test Plan'!$H:$H,"PASS") -> 3 | C4: =COUNTIFS('Test Plan'!$A:$A,A4,'Test Plan'!$H:$H,"FAIL") -> 0 | D4: =COUNTIFS('Test Plan'!$A:$A,A4,'Test Plan'!$H:$H,"PENDING") -> 0 | E4: =SUM(B4:D4) -> 3
A5: Gestion Usuarios | B5: =COUNTIFS('Test Plan'!$A:$A,A5,'Test Plan'!$H:$H,"PASS") -> 4 | C5: =COUNTIFS('Test Plan'!$A:$A,A5,'Test Plan'!$H:$H,"FAIL") -> 0 | D5: =COUNTIFS('Test Plan'!$A:$A,A5,'Test Plan'!$H:$H,"PENDING") -> 0 | E5: =SUM(B5:D5) -> 4
A6: Apertura de Turno | B6: =COUNTIFS('Test Plan'!$A:$A,A6,'Test Plan'!$H:$H,"PASS") -> 3 | C6: =COUNTIFS('Test Plan'!$A:$A,A6,'Test Plan'!$H:$H,"FAIL") -> 0 | D6: =COUNTIFS('Test Plan'!$A:$A,A6,'Test Plan'!$H:$H,"PENDING") -> 0 | E6: =SUM(B6:D6) -> 3
A7: Registro de Ventas | B7: =COUNTIFS('Test Plan'!$A:$A,A7,'Test Plan'!$H:$H,"PASS") -> 3 | C7: =COUNTIFS('Test Plan'!$A:$A,A7,'Test Plan'!$H:$H,"FAIL") -> 0 | D7: =COUNTIFS('Test Plan'!$A:$A,A7,'Test Plan'!$H:$H,"PENDING") -> 0 | E7: =SUM(B7:D7) -> 3
A8: Movimientos de Caja | B8: =COUNTIFS('Test Plan'!$A:$A,A8,'Test Plan'!$H:$H,"PASS") -> 3 | C8: =COUNTIFS('Test Plan'!$A:$A,A8,'Test Plan'!$H:$H,"FAIL") -> 0 | D8: =COUNTIFS('Test Plan'!$A:$A,A8,'Test Plan'!$H:$H,"PENDING") -> 0 | E8: =SUM(B8:D8) -> 3
A9: Cierre de Turno | B9: =COUNTIFS('Test Plan'!$A:$A,A9,'Test Plan'!$H:$H,"PASS") -> 3 | C9: =COUNTIFS('Test Plan'!$A:$A,A9,'Test Plan'!$H:$H,"FAIL") -> 0 | D9: =COUNTIFS('Test Plan'!$A:$A,A9,'Test Plan'!$H:$H,"PENDING") -> 0 | E9: =SUM(B9:D9) -> 3
A10: Arbol de Decisiones | B10: =COUNTIFS('Test Plan'!$A:$A,A10,'Test Plan'!$H:$H,"PASS") -> 4 | C10: =COUNTIFS('Test Plan'!$A:$A,A10,'Test Plan'!$H:$H,"FAIL") -> 0 | D10: =COUNTIFS('Test Plan'!$A:$A,A10,'Test Plan'!$H:$H,"PENDING") -> 0 | E10: =SUM(B10:D10) -> 4
A11: Reportes | B11: =COUNTIFS('Test Plan'!$A:$A,A11,'Test Plan'!$H:$H,"PASS") -> 3 | C11: =COUNTIFS('Test Plan'!$A:$A,A11,'Test Plan'!$H:$H,"FAIL") -> 0 | D11: =COUNTIFS('Test Plan'!$A:$A,A11,'Test Plan'!$H:$H,"PENDING") -> 0 | E11: =SUM(B11:D11) -> 3
A12: Vitrina Publica | B12: =COUNTIFS('Test Plan'!$A:$A,A12,'Test Plan'!$H:$H,"PASS") -> 4 | C12: =COUNTIFS('Test Plan'!$A:$A,A12,'Test Plan'!$H:$H,"FAIL") -> 0 | D12: =COUNTIFS('Test Plan'!$A:$A,A12,'Test Plan'!$H:$H,"PENDING") -> 0 | E12: =SUM(B12:D12) -> 4
A13: Mapa Google Maps | B13: =COUNTIFS('Test Plan'!$A:$A,A13,'Test Plan'!$H:$H,"PASS") -> 2 | C13: =COUNTIFS('Test Plan'!$A:$A,A13,'Test Plan'!$H:$H,"FAIL") -> 0 | D13: =COUNTIFS('Test Plan'!$A:$A,A13,'Test Plan'!$H:$H,"PENDING") -> 0 | E13: =SUM(B13:D13) -> 2
A14: Validacion de Botones | B14: =COUNTIFS('Test Plan'!$A:$A,A14,'Test Plan'!$H:$H,"PASS") -> 3 | C14: =COUNTIFS('Test Plan'!$A:$A,A14,'Test Plan'!$H:$H,"FAIL") -> 0 | D14: =COUNTIFS('Test Plan'!$A:$A,A14,'Test Plan'!$H:$H,"PENDING") -> 0 | E14: =SUM(B14:D14) -> 3
A15: TOTAL GENERAL | B15: =SUM(B4:B14) -> 35 | C15: =SUM(C4:C14) -> 0 | D15: =SUM(D4:D14) -> 0 | E15: =SUM(E4:E14) -> 35
A18: COBERTURA GLOBAL
A20: Estado | B20: Cantidad | C20: Porcentaje
A21: PASS | B21: =COUNTIF('Test Plan'!$H:$H,"PASS") -> 35 | C21: =IFERROR(B21/$B$24,0) -> 1
A22: FAIL | B22: =COUNTIF('Test Plan'!$H:$H,"FAIL") -> 0 | C22: =IFERROR(B22/$B$24,0) -> 0
A23: PENDING | B23: =COUNTIF('Test Plan'!$H:$H,"PENDING") -> 0 | C23: =IFERROR(B23/$B$24,0) -> 0
A24: TOTAL | B24: =SUM(B21:B23) -> 35 | C24: =SUM(C21:C23) -> 1

Sheet Tipos de Pruebas
A1: TIPOS DE PRUEBAS APLICADAS EN EL PROYECTO
A3: Tipo | B3: Descripcion | C3: Modulos en los que se aplica
A4: Funcional | B4: Verifica que cada caso de uso del sistema produzca el resultado esperado segun los criterios de aceptacion definidos en cada Historia de Usuario. | C4: Login, Gestion Usuarios, Apertura de Turno, Registro de Ventas, Movimientos de Caja, Cierre de Turno, Reportes
A5: Logica de Negocio | B5: Valida la correcta aplicacion del arbol de decisiones multivariable y los umbrales definidos para la clasificacion automatica de inconsistencias en el cierre de turno. | C5: Arbol de Decisiones, Cierre de Turno
A6: Integracion | B6: Verifica el correcto flujo de datos entre los modulos: turno -> ventas -> movimientos -> cierre -> arbol -> reportes. Comprueba que la informacion se persista correctamente entre tablas relacionadas. | C6: Registro de Ventas + Apertura de Turno + Movimientos de Caja + Cierre de Turno
A7: Seguridad / Autorizacion | B7: Valida que las rutas protegidas exijan sesion activa y el rol correspondiente. Comprueba el correcto funcionamiento del middleware de autenticacion y autorizacion por rol. | C7: Login, Gestion Usuarios, Apertura de Turno (admin only)
A8: UI / Responsive | B8: Verifica la adaptabilidad de la interfaz a diferentes dispositivos (desktop, tablet, movil) y la correcta visualizacion de elementos en distintos tamanios de pantalla. | C8: Vitrina Publica, Mapa Google Maps, Validacion de Botones
A9: Integracion Externa | B9: Valida la correcta integracion con servicios de terceros: iframe de Google Maps embebido y enlaces wa.me de WhatsApp. | C9: Mapa Google Maps, Validacion de Botones
A10: Validacion de Entrada | B10: Verifica que los formularios rechacen entradas invalidas o incompletas mostrando mensajes claros al usuario y previniendo la persistencia de datos incorrectos. | C10: Login, Gestion Usuarios, Apertura de Turno, Movimientos de Caja
A11: Persistencia de Datos | B11: Valida que las operaciones de creacion, actualizacion y desactivacion impacten correctamente en la base de datos MySQL respetando las relaciones definidas y las restricciones de integridad. | C11: Gestion Usuarios, Registro de Ventas, Cierre de Turno
